checkers_truce_simple/__init__.py
checkers_truce_simple/cts.mp3
checkers_truce_simple/cts.png
checkers_truce_simple/georgia.ttf
checkers_truce_simple/stuff.json
checkers_truce_simple/victory.wav
checkers_truce_simple/walcome.png
checkers_truce_simple/wylcomebyck.png
checkers_truce_simple-1.1.dist-info/licenses/LICENSE
checkers_truce_simple-1.1.dist-info/METADATA
checkers_truce_simple-1.1.dist-info/WHEEL
checkers_truce_simple-1.1.dist-info/entry_points.txt
checkers_truce_simple-1.1.dist-info/top_level.txt
checkers_truce_simple-1.1.dist-info/RECORD
