Metadata-Version: 2.4
Name: checkers-truce-simple
Version: 1.1
Summary: checkers truce simple
Author-email: unnamed7353 <unnamed7353@gmail.com>
Keywords: checkers,truce,simple,cts,checkerstrucesimple
Classifier: Programming Language :: Python :: 3
Classifier: License :: OSI Approved :: MIT License
Classifier: Operating System :: OS Independent
License-File: LICENSE
Requires-Dist: pygame
Dynamic: license-file
